understand_sdk/__init__.py
understand_sdk/client.py
understand_sdk/const.py
understand_sdk/examples/__init__.py
understand_sdk/examples/story.py
understand_sdk/exceptions.py
understand_sdk/model.py
understand_sdk/story.py
understand_sdk/task.py
understand_sdk-0.1.9.dist-info/LICENSE
understand_sdk-0.1.9.dist-info/METADATA
understand_sdk-0.1.9.dist-info/WHEEL
understand_sdk-0.1.9.dist-info/RECORD
