Metadata-Version: 2.3
Name: understand-sdk
Version: 0.1.9
Summary: Python client for UnderstandLabs
License: MIT
Author: Understandlabs.com Team
Author-email: it@understandlabs.com
Requires-Python: >=3.9
Classifier: License :: OSI Approved :: MIT License
Classifier: Programming Language :: Python :: 3
Classifier: Programming Language :: Python :: 3.9
Classifier: Programming Language :: Python :: 3.10
Classifier: Programming Language :: Python :: 3.11
Classifier: Programming Language :: Python :: 3.12
Classifier: Programming Language :: Python :: 3.13
Requires-Dist: pydantic (>=2.6.2,<3.0.0)
Requires-Dist: requests (>=2.31.0,<3.0.0)
